__init__.py
app.py
pisd_backup-0.0.2.dist-info/LICENSE
pisd_backup-0.0.2.dist-info/METADATA
pisd_backup-0.0.2.dist-info/WHEEL
pisd_backup-0.0.2.dist-info/top_level.txt
pisd_backup-0.0.2.dist-info/RECORD
