Metadata-Version: 2.2
Name: pisd-backup
Version: 0.0.2
Summary: Python app for creating Raspberry Pi SD card images
Author-email: Jose Ignacio Piñero <piwero@gmail.com>
Project-URL: Homepage, https://github.com/Piwero/pisd-backup
Project-URL: Issues, https://github.com/Piwero/pisd-backup/issues
Classifier: Programming Language :: Python :: 3
Classifier: Operating System :: OS Independent
Classifier: License :: OSI Approved :: MIT License
Requires-Python: >=3.11
License-File: LICENSE
Requires-Dist: python-crontab
